mr.scripty-2.0.1-py3.13-nspkg.pth
mr/scripty/README.rst
mr/scripty/__init__.py
mr/scripty/tests/__init__.py
mr/scripty/tests/test_docs.py
mr_scripty-2.0.1.dist-info/METADATA
mr_scripty-2.0.1.dist-info/WHEEL
mr_scripty-2.0.1.dist-info/entry_points.txt
mr_scripty-2.0.1.dist-info/namespace_packages.txt
mr_scripty-2.0.1.dist-info/top_level.txt
mr_scripty-2.0.1.dist-info/RECORD
