Metadata-Version: 2.2
Name: mr.scripty
Version: 2.0.1
Summary: Use python to write configuration in zc.buildout
Home-page: https://github.com/collective/mr.scripty
Author: Dylan Jay
Author-email: software@pretaweb.com
License: ZPL
Keywords: buildout
Classifier: Development Status :: 5 - Production/Stable
Classifier: Framework :: Buildout
Classifier: Intended Audience :: Developers
Classifier: Programming Language :: Python
Classifier: Programming Language :: Python :: 3 :: Only
Classifier: Programming Language :: Python :: 3.9
Classifier: Programming Language :: Python :: 3.10
Classifier: Programming Language :: Python :: 3.11
Classifier: Programming Language :: Python :: 3.12
Classifier: Programming Language :: Python :: 3.13
Classifier: Topic :: Software Development :: Build Tools
Classifier: License :: OSI Approved :: Zope Public License
Requires-Python: >=3.9
Requires-Dist: setuptools
Provides-Extra: test
Requires-Dist: zope.testing; extra == "test"
Requires-Dist: zc.buildout[test]; extra == "test"
Dynamic: author
Dynamic: author-email
Dynamic: classifier
Dynamic: description
Dynamic: home-page
Dynamic: keywords
Dynamic: license
Dynamic: provides-extra
Dynamic: requires-dist
Dynamic: requires-python
Dynamic: summary
